[
    {
        "id": 1,
        "color": "#db2828",
        "name": "aaaaaaaaaaaaaaaaa...",
        "number": "+7 (985) 512-51-20"
    },
    {
        "id": 2,
        "color": "#fbbd08",
        "name": "Голег Гегисеев",
        "number": "+7 (985) 512-51-20"
    },
    {
        "id": 3,
        "color": "#2185d0",
        "name": "Iокек Кекисеев",
        "number": "+7 (985) 512-51-20"
    },
    {
        "id": 4,
        "color": "#db2828",
        "name": "Олег Елисеев",
        "number": "+7 (985) 512-51-20"
    },
    {
        "id": 5,
        "color": "#fbbd08",
        "name": "Голег Гегисеев",
        "number": "+7 (985) 512-51-20"
    },
    {
        "id": 6,
        "color": "#2185d0",
        "name": "Iокек Кекисеев",
        "number": "+7 (985) 512-51-20"
    }
]